{"cameraMode":{"drawMode":0,"name":"Shaded","section":"Shading Mode"},"sceneLighting":true,"audioPlay":false,"sceneViewState":{"m_AlwaysRefresh":false,"showFog":true,"showSkybox":true,"showFlares":true,"showImageEffects":true,"showParticleSystems":true,"showVisualEffectGraphs":true,"m_FxEnabled":true},"in2DMode":false,"pivot":{"x":451.7175598144531,"y":27.651182174682618,"z":145.23336791992188},"rotation":{"x":0.08012928813695908,"y":-0.7304869890213013,"z":0.08655385673046112,"w":0.6727901697158814},"size":3.9930198192596437,"orthographic":false}